privex/__init__.py
privex/jsonrpc/ElectrumRPC.py
privex/jsonrpc/JsonRPC.py
privex/jsonrpc/MoneroRPC.py
privex/jsonrpc/__init__.py
privex/jsonrpc/core.py
privex/jsonrpc/helpers.py
privex/jsonrpc/objects.py
privex_jsonrpc-1.3.0.dist-info/LICENSE
privex_jsonrpc-1.3.0.dist-info/METADATA
privex_jsonrpc-1.3.0.dist-info/WHEEL
privex_jsonrpc-1.3.0.dist-info/top_level.txt
privex_jsonrpc-1.3.0.dist-info/RECORD
