Metadata-Version: 2.1
Name: privex-jsonrpc
Version: 1.3.0
Summary: A simple library for easy querying of JsonRPC services
Home-page: https://github.com/Privex/python-jsonrpc
Author: Chris (Someguy123) @ Privex
Author-email: chris@privex.io
License: MIT
Platform: UNKNOWN
Classifier: Programming Language :: Python :: 3
Classifier: Programming Language :: Python :: 3.4
Classifier: Programming Language :: Python :: 3.6
Classifier: Programming Language :: Python :: 3.7
Classifier: License :: OSI Approved :: MIT License
Classifier: Operating System :: OS Independent
Requires-Dist: requests (>=2.20.1)
